<?xml version="1.0" encoding="utf-8"?>
<LanguageData>
  <!--The following translations were generated by https://www.deepl.com/-->
  <!-- Settings -->
  <CarpenterTables.SettingsCategory>Tischler-Tische</CarpenterTables.SettingsCategory>
  <CarpenterTables.ModVersion>Installierte Mod-Version: {0}</CarpenterTables.ModVersion>
  <CarpenterTables.DeconstructInadequateProducts>Automatischer Rückbau von zusammengebauten minderwertigen Möbeln</CarpenterTables.DeconstructInadequateProducts>
  <CarpenterTables.DeconstructInadequateProducts_ToolTip>Wenn diese Einstellung aktiviert ist, bauen die Konstrukteure automatisch alle Möbel ab, die an einem Tischler-Tisch zusammengebaut wurden und nicht den Qualitätsanforderungen der Rechnung entsprechen.</CarpenterTables.DeconstructInadequateProducts_ToolTip>
  <CarpenterTables.RestrictFurnitureConstruction>Möbelbau einschränken</CarpenterTables.RestrictFurnitureConstruction>
  <CarpenterTables.RestrictFurnitureConstruction_ToolTip>Wenn diese Einstellung aktiviert ist, können Möbel nur an Schreinertischen hergestellt werden.</CarpenterTables.RestrictFurnitureConstruction_ToolTip>
</LanguageData>